eliza_gpt/__init__.py
eliza_gpt/api.py
eliza_gpt/cli.py
eliza_gpt/v1.py
eliza_gpt/eliza_py/.gitignore
eliza_gpt/eliza_py/LICENSE
eliza_gpt/eliza_py/README.md
eliza_gpt/eliza_py/demo.svg
eliza_gpt/eliza_py/eliza.py
eliza_gpt/eliza_py/flowchart.svg
eliza_gpt/eliza_py/scripts/doctor.json
eliza_gpt/eliza_py/scripts/general.json
eliza_gpt/eliza_py/utils/__init__.py
eliza_gpt/eliza_py/utils/rank.py
eliza_gpt/eliza_py/utils/response.py
eliza_gpt/eliza_py/utils/rules.py
eliza_gpt/eliza_py/utils/startup.py
eliza_gpt-0.2.0.dist-info/METADATA
eliza_gpt-0.2.0.dist-info/WHEEL
eliza_gpt-0.2.0.dist-info/entry_points.txt
eliza_gpt-0.2.0.dist-info/top_level.txt
eliza_gpt-0.2.0.dist-info/RECORD
