Metadata-Version: 2.1
Name: eliza-gpt
Version: 0.2.0
Summary: Eliza, the chatbot from the 1960s, running on OpenAI's Chat Completions API
Author-email: Miguel Grinberg <miguel.grinberg@gmail.com>
Project-URL: Homepage, https://github.com/miguelgrinberg/eliza-gpt
Project-URL: Bug Tracker, https://github.com/miguelgrinberg/eliza-gpt/issues
Classifier: Environment :: Web Environment
Classifier: Intended Audience :: Developers
Classifier: Programming Language :: Python :: 3
Classifier: License :: OSI Approved :: MIT License
Classifier: Operating System :: OS Independent
Requires-Python: >=3.8
Requires-Dist: microdot
